COPYING
COPYING.LESSER
INSTALL.rst
MANIFEST.in
README.rst
setup.cfg
setup.py
agha/__init__.py
agha.egg-info/PKG-INFO
agha.egg-info/SOURCES.txt
agha.egg-info/dependency_links.txt
agha.egg-info/not-zip-safe
agha.egg-info/requires.txt
agha.egg-info/top_level.txt