Metadata-Version: 1.1
Name: agha
Version: 0.1.0
Summary: Agha, Another GitHub API
Home-page: http://github.com/mrsarm/python-agha
Author: Mariano Ruiz
Author-email: mrsarm@gmail.com
License: LGPL-3
Download-URL: https://github.com/mrsarm/python-agha/tarball/0.1.0
Platform: any
Classifier: Development Status :: 4 - Beta
Classifier: Environment :: Web Environment
Classifier: Intended Audience :: Developers
Classifier: License :: OSI Approved :: GNU Library or Lesser General Public License (LGPL)
Classifier: Operating System :: OS Independent
Classifier: Programming Language :: Python
Classifier: Topic :: Internet :: WWW/HTTP :: Dynamic Content
Classifier: Topic :: Software Development :: Libraries :: Python Modules
